{
    "作者": "白居易",
    "詩題": "官舍",
    "3": {
        "1": {
            "1": "高",
            "2": "樹",
            "3": "換",
            "4": "新",
            "5": "葉"
        },
        "2": {
            "1": "陰",
            "2": "陰",
            "3": "覆",
            "4": "地",
            "5": "隅"
        }
    },
    "4": {
        "1": {
            "1": "何",
            "2": "言",
            "3": "太",
            "4": "守",
            "5": "宅"
        },
        "2": {
            "1": "有",
            "2": "似",
            "3": "幽",
            "4": "人",
            "5": "居"
        }
    },
    "5": {
        "1": {
            "1": "太",
            "2": "守",
            "3": "臥",
            "4": "其",
            "5": "下"
        },
        "2": {
            "1": "閒",
            "2": "慵",
            "3": "兩",
            "4": "有",
            "5": "餘"
        }
    },
    "6": {
        "1": {
            "1": "起",
            "2": "嘗",
            "3": "一",
            "4": "甌",
            "5": "茗"
        },
        "2": {
            "1": "行",
            "2": "讀",
            "3": "一",
            "4": "卷",
            "5": "書"
        }
    },
    "7": {
        "1": {
            "1": "早",
            "2": "梅",
            "3": "結",
            "4": "青",
            "5": "實"
        },
        "2": {
            "1": "殘",
            "2": "櫻",
            "3": "落",
            "4": "紅",
            "5": "珠"
        }
    },
    "8": {
        "1": {
            "1": "稚",
            "2": "女",
            "3": "弄",
            "4": "庭",
            "5": "果"
        },
        "2": {
            "1": "嬉",
            "2": "戲",
            "3": "牽",
            "4": "人",
            "5": "裾"
        }
    },
    "9": {
        "1": {
            "1": "是",
            "2": "日",
            "3": "晚",
            "4": "彌",
            "5": "靜"
        },
        "2": {
            "1": "巢",
            "2": "禽",
            "3": "下",
            "4": "相",
            "5": "呼"
        }
    },
    "10": {
        "1": {
            "1": "嘖",
            "2": "嘖",
            "3": "護",
            "4": "兒",
            "5": "鵲"
        },
        "2": {
            "1": "啞",
            "2": "啞",
            "3": "母",
            "4": "子",
            "5": "烏"
        }
    },
    "11": {
        "1": {
            "1": "豈",
            "2": "唯",
            "3": "云",
            "4": "鳥",
            "5": "爾"
        },
        "2": {
            "1": "吾",
            "2": "亦",
            "3": "引",
            "4": "吾",
            "5": "雛"
        }
    }
}